{
  "users": [
    {
      "id": 1,
      "name": "Anuj",
      "email": "saraogi.anuj9@gmail.com"
    },
    {
      "id": 2,
      "name": "Rohit",
      "email": "rohit.tripathi@gmail.com"
    }
  ],
  "bills": [
    {
      "userId": "1",
      "description": "Dinner",
      "price": "1000",
      "date": "2023-03-11",
      "id": 1
    },
    {
      "userId": "2",
      "description": "Lunch",
      "price": "2000",
      "date": "2023-03-11",
      "id": 2
    },
    {
      "userId": "2",
      "description": "Lunch",
      "price": "1000",
      "date": "2023-03-11",
      "id": 3
    },
    {
      "userId": "1",
      "description": "Clothes",
      "price": "2000",
      "date": "2023-03-11",
      "id": 4
    }
  ]
}